nembis/__init__.py
nembis/cmd/nembis.py
nembis/cmd/__init__.py
nembis/cpp/utils.cpython-310-x86_64-linux-gnu.so
nembis/cpp/ed.cpython-310-x86_64-linux-gnu.so
nembis/cpp/__init__.py
nembis/fortran/__init__.py
nembis/fortran/crystal_io.cpython-310-x86_64-linux-gnu.so
nembis/test/__init__.py
nembis/test/main.py
nembis/test/unit/test_version.py
nembis/test/unit/__init__.py
nembis/test/ed/ed.py
nembis/test/ed/__init__.py
nembis.libs/libarmadillo-66555fe4.so.10.8.0
nembis.libs/libtatlas-6cc7999c.so.3.10
nembis.libs/liblapack-1ad85175.so.3.4.2
nembis.libs/libgomp-a34b3233.so.1.0.0
nembis.libs/libarpack-7b0c1a60.so.2.0.0
nembis.libs/libquadmath-96973f99.so.0.0.0
nembis.libs/libgfortran-040039e1.so.5.0.0
nembis.libs/libsz-fcfb8163.so.2.0.1
nembis.libs/libaec-dda3378b.so.0.0.10
nembis.libs/libgfortran-91cc3cb1.so.3.0.0
nembis.libs/libhdf5-31426894.so.8.0.1
nembis.libs/libopenblaso-r0-70c28697.3.3.so
nembis.libs/libblas-357956a1.so.3.4.2
nembis-0.0.0.dist-info/top_level.txt
nembis-0.0.0.dist-info/WHEEL
nembis-0.0.0.dist-info/entry_points.txt
nembis-0.0.0.dist-info/LICENSE
nembis-0.0.0.dist-info/METADATA
nembis-0.0.0.dist-info/RECORD
